eo4eu_api_utils/__init__.py
eo4eu_api_utils/client.py
eo4eu_api_utils/workflows.py
eo4eu_api_utils-0.1.7.dist-info/METADATA
eo4eu_api_utils-0.1.7.dist-info/WHEEL
eo4eu_api_utils-0.1.7.dist-info/top_level.txt
eo4eu_api_utils-0.1.7.dist-info/RECORD
